bravas/__init__.py
bravas/example.py
bravas-0.0.1a0.dist-info/METADATA
bravas-0.0.1a0.dist-info/WHEEL
bravas-0.0.1a0.dist-info/licenses/LICENSE
bravas-0.0.1a0.dist-info/RECORD
