Metadata-Version: 2.3
Name: bravas
Version: 0.0.1a0
Summary: A unified interface for profiling and analyzing GPU applications on different platforms.
Project-URL: Homepage, https://github.com/OkkeVanEck/bravas
Project-URL: Issues, https://github.com/OkkeVanEck/bravas/issues
Author-email: Okke van Eck <okke.van.eck@gmail.com>
License-File: LICENSE
Classifier: License :: OSI Approved :: GNU General Public License v3 (GPLv3)
Classifier: Operating System :: OS Independent
Classifier: Programming Language :: Python :: 3
Requires-Python: >=3.8
